pywebasto/__init__.py
pywebasto/consts.py
pywebasto/device.py
pywebasto/enums.py
pywebasto/exceptions.py
pywebasto-2.0.0.dist-info/METADATA
pywebasto-2.0.0.dist-info/WHEEL
pywebasto-2.0.0.dist-info/licenses/LICENSE
pywebasto-2.0.0.dist-info/RECORD
