Metadata-Version: 2.4
Name: pywebasto
Version: 2.0.0
Summary: API library for Webasto ThermoConnect devices
License: MIT
License-File: LICENSE
Author: Malene Trab
Author-email: malene@trab.dk
Requires-Python: >=3.10,<4.0
Classifier: License :: OSI Approved :: MIT License
Classifier: Programming Language :: Python :: 3
Classifier: Programming Language :: Python :: 3.10
Classifier: Programming Language :: Python :: 3.11
Classifier: Programming Language :: Python :: 3.12
Classifier: Programming Language :: Python :: 3.13
Classifier: Programming Language :: Python :: 3.14
Classifier: Topic :: Software Development :: Libraries :: Python Modules
Requires-Dist: aiohttp (>=3.13.2,<4.0.0)
Project-URL: Bug Tracker, https://github.com/mtrab/pywebasto/issues
Project-URL: Documentation, https://github.com/mtrab/pywebasto
